uptimerobot_cli/__init__.py
uptimerobot_cli/utr.py
uptimerobot_cli-1.1.0.dist-info/licenses/LICENSE
uptimerobot_cli-1.1.0.dist-info/METADATA
uptimerobot_cli-1.1.0.dist-info/WHEEL
uptimerobot_cli-1.1.0.dist-info/entry_points.txt
uptimerobot_cli-1.1.0.dist-info/top_level.txt
uptimerobot_cli-1.1.0.dist-info/RECORD
