Metadata-Version: 2.4
Name: uptimerobot-cli
Version: 1.1.0
Summary: A CLI tool for UptimeRobot to help manage monitors, MWindows, etc. in a stateful way using a YAML file or by command line actions.
Author-email: "Linuxfabrik GmbH, Zurich, Switzerland" <info@linuxfabrik.ch>
License: This is free and unencumbered software released into the public domain.
Project-URL: Documentation, https://github.com/Linuxfabrik/uptimerobot/blob/master/README.md
Project-URL: Download, https://github.com/Linuxfabrik/uptimerobot/releases
Project-URL: Homepage, https://github.com/Linuxfabrik/uptimerobot
Project-URL: Source, https://github.com/Linuxfabrik/uptimerobot
Project-URL: Tracker, https://github.com/Linuxfabrik/uptimerobot/issues
Keywords: cli,uptimerobot,uptimerobot-api,monitoring
Classifier: Development Status :: 6 - Mature
Classifier: Intended Audience :: Developers
Classifier: Intended Audience :: Education
Classifier: Intended Audience :: Healthcare Industry
Classifier: Intended Audience :: Information Technology
Classifier: Intended Audience :: Manufacturing
Classifier: Intended Audience :: Other Audience
Classifier: Intended Audience :: Science/Research
Classifier: Intended Audience :: System Administrators
Classifier: Intended Audience :: Telecommunications Industry
Classifier: License :: OSI Approved :: The Unlicense (Unlicense)
Classifier: Natural Language :: English
Classifier: Operating System :: OS Independent
Classifier: Programming Language :: Python
Classifier: Programming Language :: Python :: 3
Classifier: Topic :: System
Classifier: Topic :: System :: Monitoring
Classifier: Topic :: System :: Networking :: Monitoring
Requires-Python: >=3.9
License-File: LICENSE
Requires-Dist: linuxfabrik-lib
Requires-Dist: pyyaml
Dynamic: license-file
